filesync_guardian/__init__.py
filesync_guardian/exceptions.py
filesync_guardian/sync_manager.py
filesync_guardian/encryption/__init__.py
filesync_guardian/encryption/crypto.py
filesync_guardian/encryption/key_manager.py
filesync_guardian/file_system/__init__.py
filesync_guardian/file_system/scanner.py
filesync_guardian/file_system/transfer.py
filesync_guardian/file_system/watcher.py
filesync_guardian/filters/__init__.py
filesync_guardian/filters/pattern.py
filesync_guardian/scheduler/__init__.py
filesync_guardian/storage/__init__.py
filesync_guardian/storage/ftp.py
filesync_guardian/storage/local.py
filesync_guardian/storage/s3.py
filesync_guardian/utils/__init__.py
filesync_guardian/utils/checksum.py
filesync_guardian/utils/logger.py
filesync_guardian/utils/progress.py
filesync_guardian/versioning/__init__.py
filesync_guardian/versioning/version_store.py
filesync_guardian-0.1.1.dist-info/LICENSE
filesync_guardian-0.1.1.dist-info/METADATA
filesync_guardian-0.1.1.dist-info/WHEEL
filesync_guardian-0.1.1.dist-info/top_level.txt
filesync_guardian-0.1.1.dist-info/RECORD
