Metadata-Version: 2.2
Name: filesync-guardian
Version: 0.1.1
Summary: A robust file synchronization and backup library for Python
Home-page: https://github.com/biswanathroul/filesync-guardian
Author: Biswanath Roul
Project-URL: Bug Tracker, https://github.com/biswanathroul/filesync-guardian/issues
Keywords: file,sync,backup,synchronization,versioning,encryption
Classifier: Programming Language :: Python :: 3
Classifier: Programming Language :: Python :: 3.7
Classifier: Programming Language :: Python :: 3.8
Classifier: Programming Language :: Python :: 3.9
Classifier: Programming Language :: Python :: 3.10
Classifier: License :: OSI Approved :: MIT License
Classifier: Operating System :: OS Independent
Classifier: Topic :: System :: Archiving :: Backup
Classifier: Topic :: System :: Archiving :: Mirroring
Classifier: Topic :: Utilities
Requires-Python: >=3.7
License-File: LICENSE
Requires-Dist: cryptography>=36.0.0
Dynamic: author
Dynamic: classifier
Dynamic: description
Dynamic: description-content-type
Dynamic: home-page
Dynamic: keywords
Dynamic: project-url
Dynamic: requires-dist
Dynamic: requires-python
Dynamic: summary
